Workbook

Sheet Sales
A1: Order ID | B1: Date | C1: Customer ID | D1: Product Code | E1: Quantity | F1: List Price | G1: Discount % | H1: Net Total
A2: ORD-1001 | B2: 46104 | C2: CUST-002 | D2: PRD-A01 | E2: 12 | F2: 19.99 | G2: 0 | H2: =E2*F2*(1-G2)
A3: ORD-1002 | B3: 46054 | C3: CUST-004 | D3: PRD-A02 | E3: 12 | F3: 49.99 | G3: 0 | H3: =E3*F3*(1-G3)
A4: ORD-1003 | B4: 46109 | C4: CUST-002 | D4: PRD-C01 | E4: 7 | F4: 249.99 | G4: 0 | H4: =E4*F4*(1-G4)
A5: ORD-1004 | B5: 46026 | C5: CUST-002 | D5: PRD-A02 | E5: 4 | F5: 49.99 | G5: 0.1 | H5: =E5*F5*(1-G5)
A6: ORD-1005 | B6: 46100 | C6: CUST-001 | D6: PRD-C01 | E6: 4 | F6: 249.99 | G6: 0.15 | H6: =E6*F6*(1-G6)
A7: ORD-1006 | B7: 46106 | C7: CUST-007 | D7: PRD-A02 | E7: 8 | F7: 49.99 | G7: 0.1 | H7: =E7*F7*(1-G7)
A8: ORD-1007 | B8: 46058 | C8: CUST-001 | D8: PRD-A02 | E8: 12 | F8: 49.99 | G8: 0.05 | H8: =E8*F8*(1-G8)
A9: ORD-1008 | B9: 46066 | C9: CUST-005 | D9: PRD-A02 | E9: 4 | F9: 49.99 | G9: 0.2 | H9: =E9*F9*(1-G9)
A10: ORD-1009 | B10: 46066 | C10: CUST-002 | D10: PRD-A01 | E10: 7 | F10: 19.99 | G10: 0 | H10: =E10*F10*(1-G10)
A11: ORD-1010 | B11: 46068 | C11: CUST-006 | D11: PRD-C01 | E11: 5 | F11: 249.99 | G11: 0.2 | H11: =E11*F11*(1-G11)
A12: ORD-1011 | B12: 46028 | C12: CUST-008 | D12: PRD-C01 | E12: 2 | F12: 249.99 | G12: 0.05 | H12: =E12*F12*(1-G12)
A13: ORD-1012 | B13: 46033 | C13: CUST-005 | D13: PRD-C02 | E13: 10 | F13: 399.99 | G13: 0.2 | H13: =E13*F13*(1-G13)
... A61: ORD-1060 | B61: 46075 | C61: CUST-008 | D61: PRD-B02 | E61: 4 | F61: 129.99 | G61: 0.2 | H61: =E61*F61*(1-G61)

Sheet Products
A1: Product Code | B1: Product Name | C1: Category | D1: Cost | E1: Stock
A2: PRD-A01 | B2: Coffee Mug | C2: Drinkware | D2: 4.5 | E2: 220
A3: PRD-A02 | B3: Tea Tin Set | C3: Drinkware | D3: 12 | E3: 150
A4: PRD-B01 | B4: Premium Beans 1kg | C4: Beans | D4: 28 | E4: 80
A5: PRD-B02 | B5: Espresso Bundle | C5: Bundles | D5: 55 | E5: 40
A6: PRD-C01 | B6: Coffee Grinder | C6: Equipment | D6: 110 | E6: 25
A7: PRD-C02 | B7: Espresso Machine | C7: Equipment | D7: 220 | E7: 12

Sheet Loan Model
A1: Loan Calculator
A2: Principal | B2: 250000
A3: Annual rate | B3: 0.065
A4: Years | B4: 30
A5: Periods/year | B5: 12
A6: Monthly payment | B6: =PMT(B3/B5, B4*B5, -B2)

Sheet Broken Formulas
A1: Each row has a formula error. Fix in column C.
A3: Issue | B3: Bad Formula | C3: Your Fix | D3: Hint
A4: Lookup misses target column | B4: =VLOOKUP("PRD-A01",Products!A:E,6,FALSE) | D4: Should reference an existing column index.
A5: Divide by zero | B5: =10/0 | D5: Wrap in IFERROR or fix denominator.
A6: Reference deleted cell | B6: =#REF!*2 | D6: Re-reference the correct cell.
A7: Misspelled name | B7: =SOOM(Sales!E:E) | D7: Fix the function name.
A8: Spill blocked | B8: =FILTER(Sales!A2:A60, Sales!E2:E60>5) | D8: Make sure there's room below for the spill.

Sheet Tasks
A1: Module 3 Practice — Advanced Formulas & Macros
A2: Practice tasks for this module. Try each on the data sheets, then check against the solution hints in column D.
A4: # | B4: Task | C4: Skill tested | D4: Hint
A5: 1 | B5: On the Sales sheet, in column I, use XLOOKUP to fetch the Product Name from the Products sheet for each Product Code. | C5: 3.2 Lookup | D5: =XLOOKUP(D2, Products!A:A, Products!B:B, "Not found")
A6: 2 | B6: In column J, use IFS to assign tier: >= $500 = 'A', >= $200 = 'B', otherwise 'C', based on Net Total. | C6: 3.1 Logical Operations | D6: =IFS(H2>=500,"A", H2>=200,"B", TRUE,"C")
A7: 3 | B7: In a free cell, use FILTER to show all orders where Quantity > 8 AND Discount % > 0. | C7: 3.5 Dynamic Arrays | D7: =FILTER(Sales!A2:H61, (E2:E61>8)*(G2:G61>0))
A8: 4 | B8: On Loan Model: use Goal Seek to find the principal that produces a $1,200 monthly payment at the existing rate/term. | C8: 3.4 What-If Analysis | D8: Data → What-If → Goal Seek. Set B6 to 1200 by changing B2.
A9: 5 | B9: On Loan Model: build a 1-variable Data Table showing monthly payment for rates 4%, 5%, 6%, 7%, 8%. | C9: 3.4 Data Tables | D9: Set up a column of rates, results column with =B6 formula, then Data → Data Table → Column input cell = B3.
A10: 6 | B10: Fix every formula on the Broken Formulas sheet. Use IFERROR / IFNA where appropriate. | C10: 3.7 Troubleshoot Formulas | D10: Use Trace Precedents and Evaluate Formula to debug each row.
A11: 7 | B11: Record a macro called 'FormatHeader' that bolds the active cell, fills it green, and sets white text. Save as .xlsm. | C11: 3.8 Macros | D11: Developer → Record Macro. Save the workbook as .xlsm to keep the macro.
A12: 8 | B12: On Sales, use SUMIFS to total Net Total for Customer 'CUST-001' AND Product Code starting with 'PRD-A'. | C12: 3.1 *IFS family | D12: =SUMIFS(H:H, C:C,"CUST-001", D:D,"PRD-A*")
A14: Self-check: | B14: Right-click any sheet tab → Unhide → Solutions to reveal the answer key. Try every task FIRST without peeking.

Sheet Solutions
A1: Solutions — Module 3 — Formulas & Macros
A2: These are the expected formulas / results for each Tasks sheet item. Try the task FIRST in real Excel, then peek here.
A4: # | B4: Expected solution / formula | C4: Where it lands | D4: Verification
A5: 1 | B5: =XLOOKUP(D2, Products!$A$2:$A$7, Products!$B$2:$B$7, "Not found") | C5: Sales!I2:I61 | D5: Column I matches the Product Name from the Products lookup table.
A6: 2 | B6: =IFS(H2>=500,"A", H2>=200,"B", TRUE,"C") | C6: Sales!J2:J61 | D6: Tier letter populates for every row; no #N/A or empty cells.
A7: 3 | B7: =FILTER(Sales!A2:H61, (Sales!E2:E61>8)*(Sales!G2:G61>0)) | C7: Any free cell with ~6 cols of room | D7: Result spills only orders matching both conditions; check by counting manually for a sample.
A8: 4 | B8: Data → What-If Analysis → Goal Seek. Set cell B6, To value 1200, By changing B2. | C8: Loan Model!B2 | D8: Principal updates so PMT formula in B6 = 1200. Approx $189,851 at 6.5%/30y.
A9: 5 | B9: List rates in (e.g.) E3:E7. In F2 put =B6 (link to formula). Select E2:F7. Data → What-If → Data Table → Column input cell: B3. | C9: Loan Model!E2:F7 (or similar) | D9: Each rate row shows the corresponding PMT; values rise with rate.
A10: 6 | B10: Row 4: change index 6→2. Row 5: =IFERROR(10/0, 0). Row 6: re-reference correct cell, e.g. =A1*2. Row 7: =SUM(Sales!E:E). Row 8: ensure space below the formula to spill. | C10: Broken Formulas!C4:C8 | D10: All cells in column C return a number/text — none show #REF!, #DIV/0!, #NAME?, or #SPILL!.
A11: 7 | B11: Developer → Record Macro → Name: FormatHeader. While recording: Bold (Ctrl+B), Fill Green (Home → Fill Color), Font Color White. Stop. Save As .xlsm. | C11: Stored in Personal/this workbook macro module | D11: Running FormatHeader on any cell makes it bold, green-filled, white text.
A12: 8 | B12: =SUMIFS(Sales!H:H, Sales!C:C,"CUST-001", Sales!D:D,"PRD-A*") | C12: Any cell | D12: Cross-check: filter Sales for CUST-001 + Product Codes starting PRD-A and SUM column H.
